{"chunk_definitions":[{"row":67,"row_count":1,"visible":true,"expansion_state":0,"options":{"engine":"r","label":"unnamed-chunk-3"},"document_id":"011A1E0D","chunk_id":"c5n4xb41o6lrr","chunk_label":"unnamed-chunk-2"},{"row":82,"row_count":1,"visible":true,"expansion_state":0,"options":{"engine":"r","label":"unnamed-chunk-6"},"document_id":"011A1E0D","chunk_id":"cdtsuxk6fz0ga","chunk_label":"unnamed-chunk-3"},{"row":101,"row_count":1,"visible":true,"expansion_state":0,"options":{"engine":"r","label":"unnamed-chunk-16"},"document_id":"011A1E0D","chunk_id":"cu6bukrvzlbn4","chunk_label":"unnamed-chunk-4"},{"row":105,"row_count":1,"visible":true,"expansion_state":0,"options":{"engine":"r","label":"unnamed-chunk-17"},"document_id":"011A1E0D","chunk_id":"ckpwjxvt8bm9c","chunk_label":"unnamed-chunk-5"},{"row":127,"row_count":1,"visible":true,"expansion_state":0,"options":{"engine":"r","label":"unnamed-chunk-33"},"document_id":"011A1E0D","chunk_id":"c83f8lyayiq84","chunk_label":"unnamed-chunk-7"},{"row":150,"row_count":1,"visible":true,"expansion_state":0,"options":{"engine":"r","label":"unnamed-chunk-2"},"document_id":"011A1E0D","chunk_id":"c68l85j7etua3","chunk_label":"unnamed-chunk-9"},{"row":158,"row_count":1,"visible":true,"expansion_state":0,"options":{"engine":"r","label":"unnamed-chunk-3"},"document_id":"011A1E0D","chunk_id":"c8b9bly3rpr5b","chunk_label":"unnamed-chunk-10"},{"row":183,"row_count":1,"visible":true,"expansion_state":0,"options":{"engine":"r","label":"unnamed-chunk-4"},"document_id":"011A1E0D","chunk_id":"cjctdsl3bhpk8","chunk_label":"unnamed-chunk-11"},{"row":195,"row_count":1,"visible":true,"expansion_state":0,"options":{"engine":"r","message":false,"label":"unnamed-chunk-5"},"document_id":"011A1E0D","chunk_id":"crdlfb4ltdets","chunk_label":"unnamed-chunk-12"},{"row":229,"row_count":1,"visible":true,"expansion_state":0,"options":{"engine":"r","label":"unnamed-chunk-8"},"document_id":"011A1E0D","chunk_id":"c0uxo6yg9gwqo","chunk_label":"unnamed-chunk-15"},{"row":244,"row_count":1,"visible":true,"expansion_state":0,"options":{"engine":"r","label":"unnamed-chunk-10"},"document_id":"011A1E0D","chunk_id":"c39xur9lww9w9","chunk_label":"unnamed-chunk-16"},{"row":262,"row_count":1,"visible":true,"expansion_state":0,"options":{"engine":"r","label":"unnamed-chunk-11"},"document_id":"011A1E0D","chunk_id":"colfz3mdmk8tr","chunk_label":"unnamed-chunk-17"},{"row":212,"row_count":1,"visible":true,"expansion_state":0,"options":{"engine":"r","label":"unnamed-chunk-7"},"document_id":"011A1E0D","chunk_id":"c0ib5s2lcycbj","chunk_label":"unnamed-chunk-14"},{"row":203,"row_count":1,"visible":true,"expansion_state":0,"options":{"engine":"r","label":"unnamed-chunk-6"},"document_id":"011A1E0D","chunk_id":"ce6sijw6idgzl","chunk_label":"unnamed-chunk-13"},{"row":460,"row_count":1,"visible":true,"expansion_state":0,"options":{"engine":"r","message":false,"label":"unnamed-chunk-46"},"document_id":"011A1E0D","chunk_id":"c0wjihk9lpc0l","chunk_label":"unnamed-chunk-24"},{"row":329,"row_count":1,"visible":true,"expansion_state":0,"options":{"engine":"r","label":"unnamed-chunk-13"},"document_id":"011A1E0D","chunk_id":"c5dl51mahs96t","chunk_label":"unnamed-chunk-19"},{"row":300,"row_count":1,"visible":true,"expansion_state":0,"options":{"engine":"r","label":"unnamed-chunk-12"},"document_id":"011A1E0D","chunk_id":"caxn7fu00eero","chunk_label":"unnamed-chunk-18"},{"row":480,"row_count":1,"visible":true,"expansion_state":0,"options":{"engine":"r","label":"unnamed-chunk-70"},"document_id":"011A1E0D","chunk_id":"c42if5fsgilcn","chunk_label":"unnamed-chunk-25"},{"row":348,"row_count":1,"visible":true,"expansion_state":0,"options":{"engine":"r","label":"unnamed-chunk-75"},"document_id":"011A1E0D","chunk_id":"ca4fxypuypgdj","chunk_label":"unnamed-chunk-20"},{"row":356,"row_count":1,"visible":true,"expansion_state":0,"options":{"engine":"r","label":"unnamed-chunk-78"},"document_id":"011A1E0D","chunk_id":"cjlfc832x6ult","chunk_label":"unnamed-chunk-21"},{"row":393,"row_count":1,"visible":true,"expansion_state":0,"options":{"engine":"r","label":"unnamed-chunk-79"},"document_id":"011A1E0D","chunk_id":"c7vu8pljuldok","chunk_label":"unnamed-chunk-23"}],"doc_write_time":1682677205,"chunk_rendered_width":400}